Metadata-Version: 2.1
Name: mrashid-distributions
Version: 0.1
Summary: Gaussian distributions
